cyac/__init__.py
cyac/ac.cpython-312-darwin.so
cyac/ac.pxd
cyac/ac.pyx
cyac/trie.cpython-312-darwin.so
cyac/trie.pxd
cyac/trie.pyx
cyac/unicode_portability.c
cyac/unicodetype_db.h
cyac/utf8.cpython-312-darwin.so
cyac/utf8.pxd
cyac/utf8.pyx
cyac/util.c
cyac/util.cpython-312-darwin.so
cyac/util.pxd
cyac/util.pyx
cyac/version.py
cyac/xstring.cpython-312-darwin.so
cyac/xstring.pxd
cyac/xstring.pyx
cyac-1.11.dist-info/LICENSE
cyac-1.11.dist-info/METADATA
cyac-1.11.dist-info/WHEEL
cyac-1.11.dist-info/top_level.txt
cyac-1.11.dist-info/RECORD
